[
  {
    "name": "PostActionAddPageNs",
    "type": "InsertPartialGenerationPostAction",
    "description": "Adds page namespace to shellviewmodel",
    "parameters": {
      "destination.filename": "ShellViewModel.cs",
      "destination.anchor": "//PostActionAnchor: ADD PAGE NS"
    }
  },
  {
    "name": "PostActionAddPageToNavigation",
    "type": "InsertPartialGenerationPostAction",
    "description": "Add page to navigation elements",
    "parameters": {
      "destination.filename": "ShellViewModel.cs",
      "destination.anchor": "//PostActionAnchor: ADD PAGE TO NAVIGATION"
    }
  }
]