{
  "$schema": "http://json.schemastore.org/template",
  "author": "Microsoft Community",
  "classifications": [
    "Universal"
  ],
  "name": "Page.TreeView.AddStringResources",
  "identity": "Page.TreeView.AddStringResources",
  "shortName": "Page.TreeView.AddStringResources",
  "tags": {
    "language": "C#",
    "type": "item",
    "wts.type": "composition",
    "wts.platform": "Uwp",
    "wts.version": "1.0.0",
    "wts.compositionFilter": "groupidentity == wts.Page.TreeView"
  },
  "sourceName": "wts.ItemName",
  "preferNameDirectory": true,
  "PrimaryOutputs": [
  ],
  "symbols": {
  }
}