{
    "$schema": "http://json.schemastore.org/template",
  "author": "Microsoft Community",
    "classifications": [
      "Universal"
    ],
    "name": "Page.AddTitle.TabbedNav.VB",
    "identity": "Page.AddTitle.TabbedNav.VB",
    "shortName": "Page.AddTitle.TabbedNav.VB",
    "tags": {
      "language": "VisualBasic",
      "type": "item",
      "ts.type": "composition",
      "ts.platform" : "Uwp",
      "ts.version": "1.0.0",
      "ts.compositionFilter": "$projectType == Blank|MenuBar & groupidentity == ts.Page.TabbedNav.VB"
    },
    "sourceName": "wts.ItemName",
    "preferNameDirectory": true,
    "PrimaryOutputs": [
    ],
    "symbols": {
      "ts.rootNamespace": {
        "type": "parameter",
        "replaces": "Param_RootNamespace"
      }
    }
  }
