{
  "author": "Microsoft Community Contribution",
  "classifications": [
    "Universal"
  ],
  "name": "Settings",
  "groupIdentity": "wts.Page.Settings.VB",
  "identity": "wts.Page.Settings.CodeBehind.VB",
  "description": "The settings page is the page where we recommend putting the configuration settings for your app.",
  "tags": {
    "language": "C#",
    "type": "item",
    "wts.type.VB": "page",
    "wts.framework.VB": "CodeBehind",
    "wts.version.VB": "1.0.0",
    "wts.order.VB": "2",
    "wts.dependencies.VB":"wts.Feat.SettingsStorage.VB",
    "wts.multipleInstance.VB": "false",
    "wts.genGroup.VB": "1",
    "wts.rightClickEnabled.VB":"true" 
  },
  "sourceName": "SettingsPage",
  "preferNameDirectory": true,
  "PrimaryOutputs": [
    {
      "path": ".\\Helpers\\EnumToBooleanConverter.cs"
    },
    {
      "path": ".\\Views\\SettingsPagePage.xaml"
    },
    {
      "path": ".\\Views\\SettingsPagePage.xaml.cs"
    },
    {
      "path": ".\\Services\\ThemeSelectorService.cs"
    }
  ],
  "symbols": {
    "wts.rootNamespace.VB": {
      "type": "parameter",
      "replaces": "Param_RootNamespace"
    },
    "wts.itemNamespace.VB": {
      "type": "parameter",
      "replaces": "Param_ItemNamespace"
    },
    "baseclass": {
      "type": "parameter",
      "replaces": "System.ComponentModel.INotifyPropertyChanged"
    },
    "setter": {
      "type": "parameter",
      "replaces": "Set"
    }
  }
}
