{
  "$schema": "http://json.schemastore.org/template",
  "author": "Microsoft Community",
  "classifications": [
    "Universal"
  ],
  "name": "MVVMToolkit.Page.TreeView",
  "identity": "MVVMToolkit.Page.TreeView",
  "shortName": "MVVMToolkit.Page.TreeView",
  "tags": {
    "language": "C#",
    "type": "item",
    "ts.type": "composition",
    "ts.platform" : "Uwp",
    "ts.version": "1.0.0",
    "ts.compositionFilter": "$frontendframework == MVVMToolkit & groupidentity == ts.Page.TreeView"
  },
  "sourceName": "wts.ItemName",
  "preferNameDirectory": true,
  "PrimaryOutputs": [
  ],
  "symbols": {
    "wts.rootNamespace": {
      "type": "parameter",
      "replaces": "Param_RootNamespace"
    },
    "baseclass": {
      "type": "parameter",
      "replaces": "System.ComponentModel.INotifyPropertyChanged"
    }
  }
}
