{
  "author": "Microsoft Community Contribution",
  "classifications": [
    "Universal"
  ],
  "name": "Dev Center Notifications",
  "groupIdentity": "wts.Feat.StoreNotifications.VB",
  "identity": "wts.Feat.StoreNotifications.VB",
  "description": "Register your app to receive notifications from the store and handle them being used to launch the app.",
  "tags": {
    "language": "C#",
    "type": "item",
    "wts.type.VB": "feature",
    "wts.framework.VB": "MVVMBasic|MVVMLight|CodeBehind",
    "wts.version.VB": "1.0.0",
    "wts.order.VB": "2",
    "wts.group.VB": "UserInteraction",
    "wts.licenses.VB": "[Microsoft.Services.Store.SDK](https://www.microsoft.com/legal/intellectualproperty/copyright/default.aspx)",
    "wts.defaultInstance.VB": "StoreNotifications",
    "wts.multipleInstance.VB": "false",
    "wts.genGroup.VB": "0",
    "wts.rightClickEnabled.VB":"true"
  },
  "sourceName": "StoreNotificationsFeature",
  "preferNameDirectory": true,
  "PrimaryOutputs": [
    {
      "path": ".\\Services\\StoreNotificationsFeatureService.cs"
    }
  ],
  "symbols": {
    "wts.rootNamespace.VB": {
      "type": "parameter",
      "replaces": "Param_RootNamespace"
    },
    "wts.itemNamespace.VB": {
      "type": "parameter",
      "replaces": "Param_ItemNamespace"
    }
  }
}
