{
  "author": "Microsoft",
  "classifications": ["Universal"],
  "name": "Suspend and Resume",
  "groupIdentity": "wts.Feat.SuspendAndResume",
  "identity": "wts.Feat.SuspendAndResume",
  "shortName": "Suspend and Resume",
  "description": "A user can suspend your app at any time so let's be ready for it.  We have a nifty suspend and resume service you can hook into.",
  "tags": {
    "language": "C#",
    "type": "item",
    "wts.type": "feature",
    "wts.framework": "MVVMBasic|MVVMLight|CodeBehind",
    "wts.version": "1.0.0",
    "wts.order": "1",
    "wts.group": "ApplicationLifecycle",
    "wts.multipleInstance": "false",
    "wts.defaultInstance": "SuspendAndResume",
    "wts.dependencies":"wts.Feat.SettingsStorage"
  },
  "sourceName": "SuspendAndResumeFeature",
  "preferNameDirectory": true,
  "guids": [ "5b9d2eee-b648-4ca1-837e-9abb8f3dffdd" ],
  "PrimaryOutputs": [
    {
      "path": ".\\Services\\SuspendAndResumeService.cs"
    },
    {
      "path": ".\\Services\\OnBackgroundEnteringEventArgs.cs"
    },
    {
      "path": ".\\Services\\SuspensionState.cs"
    }
  ],
  "symbols": {
    "wts.rootNamespace": {
      "type": "parameter",
      "replaces": "Param_RootNamespace"
    },
    "wts.itemNamespace": {
      "type": "parameter",
      "replaces": "Param_ItemNamespace"
    }
  }
}